prodiguer_client-0.1.0.2.data/purelib/prodiguer_client/__init__.py
prodiguer_client-0.1.0.2.data/purelib/prodiguer_client/exceptions.py
prodiguer_client-0.1.0.2.data/purelib/prodiguer_client/options.py
prodiguer_client-0.1.0.2.data/purelib/prodiguer_client/metrics/__init__.py
prodiguer_client-0.1.0.2.data/purelib/prodiguer_client/metrics/api_proxy.py
prodiguer_client-0.1.0.2.data/purelib/prodiguer_client/metrics/formatter/__init__.py
prodiguer_client-0.1.0.2.data/purelib/prodiguer_client/metrics/formatter/constants.py
prodiguer_client-0.1.0.2.data/purelib/prodiguer_client/metrics/formatter/decoder.py
prodiguer_client-0.1.0.2.data/purelib/prodiguer_client/metrics/formatter/decoder_pcmdi.py
prodiguer_client-0.1.0.2.data/purelib/prodiguer_client/metrics/formatter/encoder.py
prodiguer_client-0.1.0.2.data/purelib/prodiguer_client/metrics/formatter/encoder_blocks.py
prodiguer_client-0.1.0.2.data/purelib/prodiguer_client/metrics/formatter/hashifier.py
prodiguer_client-0.1.0.2.data/purelib/prodiguer_client/metrics/formatter/io.py
prodiguer_client-0.1.0.2.data/purelib/prodiguer_client/metrics/formatter/main.py
prodiguer_client-0.1.0.2.data/purelib/prodiguer_client/metrics/formatter/transformer.py
prodiguer_client-0.1.0.2.data/purelib/prodiguer_client/metrics/formatter/transformer_pcmdi.py
prodiguer_client-0.1.0.2.data/purelib/prodiguer_client/metrics/formatter/transformer_utils.py
prodiguer_client-0.1.0.2.data/purelib/prodiguer_client/ops/__init__.py
prodiguer_client-0.1.0.2.data/purelib/prodiguer_client/ops/api_proxy.py
prodiguer_client-0.1.0.2.data/purelib/prodiguer_client/utils/__init__.py
prodiguer_client-0.1.0.2.data/purelib/prodiguer_client/utils/api.py
prodiguer_client-0.1.0.2.data/purelib/prodiguer_client/utils/convert.py
prodiguer_client-0.1.0.2.data/purelib/prodiguer_client/utils/io.py
prodiguer_client-0.1.0.2.data/purelib/prodiguer_client/utils/runtime.py
prodiguer_client-0.1.0.2.dist-info/DESCRIPTION.rst
prodiguer_client-0.1.0.2.dist-info/METADATA
prodiguer_client-0.1.0.2.dist-info/metadata.json
prodiguer_client-0.1.0.2.dist-info/RECORD
prodiguer_client-0.1.0.2.dist-info/top_level.txt
prodiguer_client-0.1.0.2.dist-info/WHEEL
